LICENSE
MANIFEST.in
README.md
pyproject.toml
setup.cfg
myplotlib/__init__.py
myplotlib/plots.py
myplotlib/tests.py
myplotlib.egg-info/PKG-INFO
myplotlib.egg-info/SOURCES.txt
myplotlib.egg-info/dependency_links.txt
myplotlib.egg-info/requires.txt
myplotlib.egg-info/top_level.txt
myplotlib.egg-info/zip-safe
myplotlib/assets/fancy.dark.mplstyle
myplotlib/assets/fancy.light.mplstyle
myplotlib/assets/hershey.dark.mplstyle
myplotlib/assets/hershey.light.mplstyle
myplotlib/assets/mono.dark.mplstyle
myplotlib/assets/mono.light.mplstyle
myplotlib/assets/colormaps/bipolar.csv
myplotlib/assets/colormaps/colt.csv
myplotlib/assets/colormaps/fire.csv
myplotlib/assets/colormaps/idl.csv
myplotlib/assets/colormaps/sunrise.csv
myplotlib/assets/colormaps/thermal.csv
myplotlib/assets/colormaps/vanilla.csv
myplotlib/assets/fonts/AppleChancery.ttf
myplotlib/assets/fonts/EBGaramond-Bold.ttf
myplotlib/assets/fonts/EBGaramond-BoldItalic.ttf
myplotlib/assets/fonts/EBGaramond-ExtraBold.ttf
myplotlib/assets/fonts/EBGaramond-ExtraBoldItalic.ttf
myplotlib/assets/fonts/EBGaramond-Italic.ttf
myplotlib/assets/fonts/EBGaramond-Medium.ttf
myplotlib/assets/fonts/EBGaramond-MediumItalic.ttf
myplotlib/assets/fonts/EBGaramond-Regular.ttf
myplotlib/assets/fonts/EBGaramond-SemiBold.ttf
myplotlib/assets/fonts/EBGaramond-SemiBoldItalic.ttf
myplotlib/assets/fonts/HersheyTex-Book.otf
myplotlib/assets/fonts/HersheyTex-Light.otf
myplotlib/tools/__init__.py
myplotlib/tools/lic.py