Metadata-Version: 2.1
Name: myplotlib
Version: 1.1.0
Summary: `matplotlib` binder with custom styles and routines for fast plotting
Home-page: https://github.com/haykh/myplotlib
Author: morninbru
Author-email: haykh.astro@gmail.com
License: BSD 3-Clause License
Requires-Python: >=3.6
Provides-Extra: dev
License-File: LICENSE
